streamrecord/__main__.py
streamrecord/appinspector.py
streamrecord/encoder.py
streamrecord/pulseaudiomanager.py
streamrecord/songwriter.py
streamrecord/streamloader.py
streamrecord-0.9.1.dist-info/DESCRIPTION.rst
streamrecord-0.9.1.dist-info/METADATA
streamrecord-0.9.1.dist-info/RECORD
streamrecord-0.9.1.dist-info/WHEEL
streamrecord-0.9.1.dist-info/entry_points.txt
streamrecord-0.9.1.dist-info/metadata.json
streamrecord-0.9.1.dist-info/top_level.txt
streamrecord-0.9.1.dist-info/zip-safe
