Metadata-Version: 2.0
Name: streamrecord
Version: 0.9.1
Summary: Record and split an audio stream
Home-page: http://github.com/AlexisBRENON/deezer_record
Author: Alexis BRENON
Author-email: brenon.alexis+streamrecord@gmail.com
License: MIT
Keywords: audio stream record
Platform: UNKNOWN
Classifier: Development Status :: 4 - Beta
Classifier: Environment :: Console
Classifier: Intended Audience :: End Users/Desktop
Classifier: License :: OSI Approved :: MIT License
Classifier: Natural Language :: English
Classifier: Programming Language :: Python :: 3
Classifier: Topic :: Multimedia :: Sound/Audio :: Capture/Recording
Classifier: Topic :: Utilities
Requires-Python: >=3
Requires-Dist: python-slugify
Requires-Dist: python-xlib
Requires-Dist: dbus-python
Requires-Dist: notify2
